<?xml version="1.0" encoding="UTF-8" ?> 
 <!DOCTYPE configuration PUBLIC "-//mybatis.org//DTD Config 3.0//EN"
"http://mybatis.org/dtd/mybatis-3-config.dtd"> 
<configuration>
	<typeAliases>
	</typeAliases>
	<mappers>
		<mapper resource="mapper/portals/AttachmentDaoMapper.xml" />
		<mapper resource="mapper/portals/SurveyDaoMapper.xml" />
		<mapper resource="mapper/portals/SurveyAnswerDaoMapper.xml" />
		<mapper resource="mapper/portals/SurveyQuestionDaoMapper.xml" />
		<mapper resource="mapper/portals/ContentDaoMapper.xml" />
		<mapper resource="mapper/portals/MarqueeDaoMapper.xml" />
		<mapper resource="mapper/portals/MarqueePublishDaoMapper.xml" />
		<mapper resource="mapper/portals/KnowledgeDaoMapper.xml" />
	</mappers>
</configuration>
